fitree/__init__.py
fitree/_inference/__init__.py
fitree/_inference/_backend.py
fitree/_inference/_initialization.py
fitree/_inference/_likelihood.py
fitree/_inference/_prior.py
fitree/_inference/_utils.py
fitree/_plot/__init__.py
fitree/_plot/_fmat.py
fitree/_plot/_tree.py
fitree/_simulation/__init__.py
fitree/_simulation/_fmat.py
fitree/_simulation/_simulate.py
fitree/_simulation/_utils.py
fitree/_trees/__init__.py
fitree/_trees/_cohort.py
fitree/_trees/_io.py
fitree/_trees/_subclone.py
fitree/_trees/_tumor.py
fitree/_trees/_wrapper.py
fitree-0.1.0.dist-info/LICENSE
fitree-0.1.0.dist-info/METADATA
fitree-0.1.0.dist-info/WHEEL
fitree-0.1.0.dist-info/RECORD
