Metadata-Version: 2.1
Name: fitree
Version: 0.1.0
Summary: 
Author: Computational Biology Group
Requires-Python: >=3.11,<3.13
Classifier: Programming Language :: Python :: 3
Classifier: Programming Language :: Python :: 3.11
Requires-Dist: anytree (>=2.9.0,<3.0.0)
Requires-Dist: graphviz (>=0.20.3,<0.21.0)
Requires-Dist: ipython (>=8.28.0,<9.0.0)
Requires-Dist: jax (>=0.4.30,<0.5.0)
Requires-Dist: numpy (>=1.26.0,<2.0.0)
Requires-Dist: pymc (>=5.8.2,<6.0.0)
Requires-Dist: scipy (>=1.14.1,<2.0.0)
Requires-Dist: seaborn (>=0.13.2,<0.14.0)
Requires-Dist: snakemake (>=8.14.0,<9.0.0)
